maap_libs_jupyter_extension/__init__.py
maap_libs_jupyter_extension/_version.py
maap_libs_jupyter_extension-1.2.5.data/data/share/jupyter/labextensions/maap_libs_jupyter_extension/package.json
maap_libs_jupyter_extension-1.2.5.data/data/share/jupyter/labextensions/maap_libs_jupyter_extension/static/631.0400b435341dc3a4ce27.js
maap_libs_jupyter_extension-1.2.5.data/data/share/jupyter/labextensions/maap_libs_jupyter_extension/static/821.b1e9b670158573fce10f.js
maap_libs_jupyter_extension-1.2.5.data/data/share/jupyter/labextensions/maap_libs_jupyter_extension/static/remoteEntry.df617213481178fd8aba.js
maap_libs_jupyter_extension-1.2.5.data/data/share/jupyter/labextensions/maap_libs_jupyter_extension/static/style.js
maap_libs_jupyter_extension-1.2.5.data/data/share/jupyter/labextensions/maap_libs_jupyter_extension/static/third-party-licenses.json
maap_libs_jupyter_extension-1.2.5.data/data/share/jupyter/labextensions/maap_libs_jupyter_extension/install.json
maap_libs_jupyter_extension-1.2.5.dist-info/METADATA
maap_libs_jupyter_extension-1.2.5.dist-info/WHEEL
maap_libs_jupyter_extension-1.2.5.dist-info/licenses/LICENSE
maap_libs_jupyter_extension-1.2.5.dist-info/RECORD
