Metadata-Version: 2.4
Name: maap_libs_jupyter_extension
Version: 1.2.5
Dynamic: Keywords
Summary: Import MAAP tools and libraries easily into your Jupyter notebook.
Project-URL: Homepage, https://github.com/MAAP-Project/maap-libs-jupyter-extension
Project-URL: Bug Tracker, https://github.com/MAAP-Project/maap-libs-jupyter-extension/issues
Project-URL: Repository, https://github.com/MAAP-Project/maap-libs-jupyter-extension.git
Author-email: Marjorie Lucas <marjorie.j.lucas@jpl.nasa.gov>
License:                                  Apache License
License-File: LICENSE
Classifier: Framework :: Jupyter
Classifier: Framework :: Jupyter :: JupyterLab
Classifier: Framework :: Jupyter :: JupyterLab :: 4
Classifier: Framework :: Jupyter :: JupyterLab :: Extensions
Classifier: Framework :: Jupyter :: JupyterLab :: Extensions :: Prebuilt
Classifier: License :: OSI Approved :: BSD License
Classifier: Programming Language :: Python
Classifier: Programming Language :: Python :: 3
Classifier: Programming Language :: Python :: 3.8
Classifier: Programming Language :: Python :: 3.9
Classifier: Programming Language :: Python :: 3.10
Classifier: Programming Language :: Python :: 3.11
Classifier: Programming Language :: Python :: 3.12
Requires-Python: >=3.8
Provides-Extra: test
Requires-Dist: coverage; extra == 'test'
Requires-Dist: pytest; extra == 'test'
Requires-Dist: pytest-asyncio; extra == 'test'
Requires-Dist: pytest-cov; extra == 'test'
Requires-Dist: pytest-jupyter[server]>=0.6.0; extra == 'test'
